pivtools-0.4.2.dist-info/licenses/LICENSE
pivtools-0.4.2.dist-info/licenses/NOTICE
pivtools_cli/__init__.py
pivtools_cli/cli.py
pivtools_cli/lib/PIV_2d_cross_correlate.c
pivtools_cli/lib/PIV_2d_cross_correlate.h
pivtools_cli/lib/common.h
pivtools_cli/lib/interp2custom.c
pivtools_cli/lib/interp2custom.h
pivtools_cli/lib/libbulkxcorr2d.dll
pivtools_cli/lib/libinterp2custom.dll
pivtools_cli/lib/libmarquadt.dll
pivtools_cli/lib/marquadt_gaussian.c
pivtools_cli/lib/marquadt_gaussian.h
pivtools_cli/lib/peak_locate_lm.c
pivtools_cli/lib/peak_locate_lm.h
pivtools_cli/lib/xcorr.c
pivtools_cli/lib/xcorr.h
pivtools_cli/lib/xcorr_cache.c
pivtools_cli/lib/xcorr_cache.h
pivtools_cli/piv/gradient_correction.py
pivtools_cli/piv/piv.py
pivtools_cli/piv/piv_result.py
pivtools_cli/piv/save_results.py
pivtools_cli/piv/interp2custom/interp2custom.py
pivtools_cli/piv/piv_backend/base.py
pivtools_cli/piv/piv_backend/cpu_ensemble.py
pivtools_cli/piv/piv_backend/cpu_instantaneous.py
pivtools_cli/piv/piv_backend/debug_plotting.py
pivtools_cli/piv/piv_backend/factory.py
pivtools_cli/piv/piv_backend/gaussian_fitting.py
pivtools_cli/piv/piv_backend/gpu_instantaneous.py
pivtools_cli/piv/piv_backend/infilling.py
pivtools_cli/piv/piv_backend/kspace_fitting.py
pivtools_cli/piv/piv_backend/outlier_detection.py
pivtools_cli/piv/piv_backend/single_pass_accumulator.py
pivtools_cli/piv_cluster/cluster.py
pivtools_cli/preprocessing/diagnostics.py
pivtools_cli/preprocessing/filters.py
pivtools_cli/preprocessing/pod_filter.py
pivtools_cli/preprocessing/preprocess.py
pivtools_cli/processing/__init__.py
pivtools_cli/processing/dask_pipeline.py
pivtools_cli/tests/helpers.py
pivtools_cli/tests/instantaneous_piv/test_piv_integration.py
pivtools_cli/tests/instantaneous_piv/test_piv_integration_multi.py
pivtools_cli/tests/preprocessing/test_filters.py
pivtools_core/__init__.py
pivtools_core/batch_utils.py
pivtools_core/config.py
pivtools_core/coordinate_utils.py
pivtools_core/ensemble.py
pivtools_core/instantaneous.py
pivtools_core/paths.py
pivtools_core/validation.py
pivtools-0.4.2.dist-info/METADATA
pivtools-0.4.2.dist-info/WHEEL
pivtools-0.4.2.dist-info/entry_points.txt
pivtools-0.4.2.dist-info/top_level.txt
pivtools-0.4.2.dist-info/RECORD
