Metadata-Version: 2.4
Name: pivtools
Version: 0.4.2
Summary: PIVTOOLs - Particle Image Velocimetry Tools with CLI and GUI
Author-email: Morgan Taylor <m.t.taylor@soton.ac.uk>
License-Expression: BSD-3-Clause
Project-URL: Homepage, https://github.com/MTT69/python-PIVTOOLs
Project-URL: Repository, https://github.com/MTT69/python-PIVTOOLs
Project-URL: Issues, https://github.com/MTT69/python-PIVTOOLs/issues
Classifier: Development Status :: 4 - Beta
Classifier: Intended Audience :: Science/Research
Classifier: Operating System :: OS Independent
Classifier: Programming Language :: Python :: 3
Classifier: Programming Language :: Python :: 3.12
Classifier: Programming Language :: Python :: 3.13
Classifier: Topic :: Scientific/Engineering :: Image Processing
Classifier: Framework :: Flask
Requires-Python: >=3.12
License-File: LICENSE
License-File: NOTICE
Requires-Dist: dask[distributed]==2025.7.0
Requires-Dist: dask-jobqueue
Requires-Dist: dask-image
Requires-Dist: loguru==0.7.3
Requires-Dist: numpy==2.2.6
Requires-Dist: opencv-python==4.12.0.88
Requires-Dist: pandas==2.3.1
Requires-Dist: pillow==11.3.0
Requires-Dist: PyYAML==6.0.2
Requires-Dist: scipy==1.16.1
Requires-Dist: tifffile==2025.6.11
Requires-Dist: tqdm==4.67.1
Requires-Dist: numba==0.61.2
Requires-Dist: psutil==6.1.1
Requires-Dist: pytest==8.4.2
Requires-Dist: rawpy==0.25.1
Requires-Dist: scikit-image==0.25.2
Requires-Dist: lvpyio==1.3.1; sys_platform != "darwin"
Requires-Dist: bottleneck==1.6.0
Requires-Dist: scikit-learn==1.7.2
Requires-Dist: threadpoolctl==3.6.0
Requires-Dist: Flask==3.1.1
Requires-Dist: flask-cors==6.0.1
Requires-Dist: matplotlib==3.10.5
Requires-Dist: imagecodecs
Requires-Dist: imageio-ffmpeg>=0.5.0
Dynamic: license-file
